pyducc/__init__.py
pyducc/client.py
pyducc/properties.py
pyducc-0.1.3.dist-info/METADATA
pyducc-0.1.3.dist-info/WHEEL
pyducc-0.1.3.dist-info/top_level.txt
pyducc-0.1.3.dist-info/RECORD
