Metadata-Version: 2.1
Name: pyducc
Version: 0.1.3
Summary: Python DUCC Client - 用于与DUCC服务通信获取配置并管理配置更新的客户端
Author-email: JK-AI Team <xuguozhi@jd.com>
License: MIT
Project-URL: Homepage, https://coding.jd.com/xuguozhi/pyducc.git
Project-URL: Bug Tracker, https://coding.jd.com/xuguozhi/pyducc.git
Keywords: ducc,configuration,client
Classifier: Development Status :: 4 - Beta
Classifier: Intended Audience :: Developers
Classifier: License :: OSI Approved :: MIT License
Classifier: Programming Language :: Python :: 3
Classifier: Programming Language :: Python :: 3.8
Classifier: Programming Language :: Python :: 3.9
Classifier: Programming Language :: Python :: 3.10
Classifier: Programming Language :: Python :: 3.11
Classifier: Topic :: Software Development :: Libraries :: Python Modules
Requires-Python: >=3.8
Requires-Dist: requests >=2.32.4
Requires-Dist: six >=1.17.0
